pipetography/__init__.py
pipetography/_nbdev.py
pipetography/connectomes.py
pipetography/core.py
pipetography/knots.py
pipetography/nodes.py
pipetography/pipeline.py
pipetography-0.3.12.dist-info/LICENSE
pipetography-0.3.12.dist-info/METADATA
pipetography-0.3.12.dist-info/WHEEL
pipetography-0.3.12.dist-info/entry_points.txt
pipetography-0.3.12.dist-info/top_level.txt
pipetography-0.3.12.dist-info/RECORD
