Metadata-Version: 2.1
Name: pipetography
Version: 0.3.12
Summary: Pre/Post-processing pipeline for tractography wrapped around nipype and mrtrix3
Home-page: https://github.com/axiezai/pipetography
Author: Xi He Xie
Author-email: axiezai@gmail.com
License: Apache Software License 2.0
Keywords: diffusion-mri,tractography,neuroimaging,nipype
Platform: UNKNOWN
Classifier: Development Status :: 5 - Production/Stable
Classifier: Intended Audience :: Developers
Classifier: License :: OSI Approved :: Apache Software License
Classifier: Natural Language :: English
Classifier: Programming Language :: Python :: 3.6
Classifier: Programming Language :: Python :: 3.7
Classifier: Programming Language :: Python :: 3.8
Requires-Python: >=3.6
Requires-Dist: ipython
Requires-Dist: nilearn
Requires-Dist: dipy
Requires-Dist: nibabel
Requires-Dist: pybids
Requires-Dist: matplotlib
Requires-Dist: nipype
Requires-Dist: fastcore
